quantlof/__init__.py
quantlof/quantum_lof_classifier.py
quantlof-0.1.5.dist-info/licenses/LICENSE.m
quantlof-0.1.5.dist-info/METADATA
quantlof-0.1.5.dist-info/WHEEL
quantlof-0.1.5.dist-info/top_level.txt
quantlof-0.1.5.dist-info/RECORD
