Metadata-Version: 2.4
Name: quantlof
Version: 0.1.5
Summary: Quantum-enhanced Local Outlier Factor algorithm
Author: Yuto Mueller
Author-email: geoyuto@gmail.com
License: MIT
Requires-Python: >=3.8
License-File: LICENSE.m
Requires-Dist: qiskit==2.0.2
Requires-Dist: qiskit-aer==0.17.0
Requires-Dist: qiskit-ibm-runtime==0.40.0
Requires-Dist: scikit-learn==1.6.1
Requires-Dist: scipy==1.15.3
Requires-Dist: numpy==2.2.6
Dynamic: author
Dynamic: author-email
Dynamic: description
Dynamic: description-content-type
Dynamic: license
Dynamic: license-file
Dynamic: requires-dist
Dynamic: requires-python
Dynamic: summary
